obragtools/query/__init__.py
obragtools/query/core.py
obragtools/reader/__init__.py
obragtools/reader/function.py
obragtools/reader/reader.py
obragtools/reader/utils.py
obragtools-0.1.3.dist-info/METADATA
obragtools-0.1.3.dist-info/WHEEL
obragtools-0.1.3.dist-info/top_level.txt
obragtools-0.1.3.dist-info/RECORD
