Metadata-Version: 2.4
Name: obragtools
Version: 0.1.3
Summary: 优化了issue 
Requires-Python: >=3.10
Requires-Dist: llama-index>=0.12.28
Requires-Dist: llama-index-readers-github>=0.6.0
Requires-Dist: pinecone>=6.0.2
Requires-Dist: pytest>=8.3.5
Requires-Dist: pytest-html>=4.1.1
Requires-Dist: setuptools>=78.1.0
